{
  "title": "MOODBASE",
  "description": "Die intelligente Plattform für psychosoziale Unterstützungsangebote.",
  "sections": [
    {
      "title": "Über uns",
      "links": [
        { "label": "Unsere Mission", "url": "#" },
        { "label": "Das Team", "url": "#" },
        { "label": "Karriere", "url": "#" }
      ]
    },
    { 
      "title": "Community",
      "links": [
        { "label": "Für Anbieter", "url": "#" },
        { "label": "Partnerschaften", "url": "#" },
        { "label": "Blog", "url": "#" }
      ]
    },
    {
      "title": "Hilfe",
      "links": [
        { "label": "FAQ", "url": "#" },
        { "label": "Kontakt", "url": "#" },
        { "label": "Impressum", "url": "#" }
      ]
    }
  ],
  "copyright": "© 2025 Moodbase. Alle Rechte vorbehalten."
}